scorpiui/_init__.py
scorpiui/app.py
scorpiui/event_handler.py
scorpiui/components/__init__.py
scorpiui/components/button.py
scorpiui/components/text_input.py
scorpiui/templates/base.html
scorpiui-0.0.1.dist-info/METADATA
scorpiui-0.0.1.dist-info/WHEEL
scorpiui-0.0.1.dist-info/licenses/LICENSE
scorpiui-0.0.1.dist-info/RECORD
