Metadata-Version: 2.3
Name: scorpiui
Version: 0.0.1
Summary: ScorpiUI: A Python UI library for building web apps with minimal HTML, CSS, and JS.
Project-URL: Homepage, https://github.com/gladsonchala/scorpiui
Project-URL: Issues, https://github.com/gladsonchala/scorpiui/issues
Author-email: "Gemechis Chala (ScorpiDev)" <gladsonchala@gmail.com>
License-File: LICENSE
Classifier: Development Status :: 3 - Alpha
Classifier: Intended Audience :: Developers
Classifier: License :: OSI Approved :: MIT License
Classifier: Operating System :: OS Independent
Classifier: Programming Language :: Python :: 3
Classifier: Programming Language :: Python :: 3.6
Classifier: Programming Language :: Python :: 3.7
Classifier: Programming Language :: Python :: 3.8
Classifier: Programming Language :: Python :: 3.9
Classifier: Programming Language :: Python :: 3.10
Classifier: Programming Language :: Python :: 3.11
Classifier: Topic :: Software Development :: Libraries :: Application Frameworks
Requires-Python: >=3.8
